Metadata-Version: 2.1
Name: SimpleMyAI
Version: 4.2
Summary: Easy creation of your own simple neural network
Author-email: samkirich@yandex.ru
